triangularmap/__init__.py
triangularmap/tmap.py
triangularmap-0.1.2.dist-info/LICENSE
triangularmap-0.1.2.dist-info/METADATA
triangularmap-0.1.2.dist-info/WHEEL
triangularmap-0.1.2.dist-info/top_level.txt
triangularmap-0.1.2.dist-info/RECORD
