Metadata-Version: 2.1
Name: triangularmap
Version: 0.1.2
Summary: A Python library for working with triangular maps stored in linear arrays.
Home-page: https://github.com/robert-lieck/triangularmap
Author: Robert Lieck
Author-email: robert.lieck@durham.ac.uk
Classifier: Programming Language :: Python :: 3
Classifier: License :: OSI Approved :: GNU General Public License v3 (GPLv3)
Classifier: Operating System :: OS Independent
Requires-Python: >=3.8
License-File: LICENSE
Requires-Dist: numpy
Requires-Dist: torch
